richbench/__init__.py
richbench/__main__.py
richbench-1.0.3.dist-info/entry_points.txt
richbench-1.0.3.dist-info/LICENSE
richbench-1.0.3.dist-info/WHEEL
richbench-1.0.3.dist-info/METADATA
richbench-1.0.3.dist-info/RECORD
