Metadata-Version: 2.1
Name: richbench
Version: 1.0.3
Summary: Richbench, a little benchmarking tool
Author: Anthony Shaw
Requires-Python: >=3.6
Classifier: License :: OSI Approved :: MIT License
Requires-Dist: rich
Requires-Dist: pyinstrument
Project-URL: Home, https://github.com/tonybaloney/rich-bench
